qkun/__init__.py
qkun/geobox.py
qkun/api/__init__.py
qkun/api/digest_granule.py
qkun/api/download_elevation.py
qkun/api/download_granule.py
qkun/api/search_granule.py
qkun/cmr/__init__.py
qkun/cmr/granule_download.py
qkun/cmr/granule_search.py
qkun/cmr/product_catalog.py
qkun/cmr/products.yaml
qkun/granule/__init__.py
qkun/granule/append_resolution.py
qkun/granule/compute_alpha_envelope.py
qkun/granule/granule_handler.py
qkun/granule/serializer.py
qkun/nc/__init__.py
qkun/nc/nc_global_to_yaml.py
qkun/nc/nc_utils.py
qkun/nc/nc_variable_to_yaml.py
qkun/pace/__init__.py
qkun/pace/ocean_color.py
qkun-0.4.1.dist-info/licenses/LICENSE
qkun-0.4.1.dist-info/METADATA
qkun-0.4.1.dist-info/WHEEL
qkun-0.4.1.dist-info/entry_points.txt
qkun-0.4.1.dist-info/top_level.txt
qkun-0.4.1.dist-info/RECORD
