Metadata-Version: 2.4
Name: qkun
Version: 0.4.1
Summary: Geoinformation Tools & Data Access for Satellite Observations
Author-email: Cheng Li <chengcli@umich.edu>
License-Expression: MIT
Project-URL: Homepage, https://github.com/chengcli/qkun
Project-URL: Documentation, https://github.com/chengcli/qkun
Requires-Python: >=3.9
License-File: LICENSE
Requires-Dist: numpy
Requires-Dist: pyproj
Requires-Dist: matplotlib
Requires-Dist: cartopy
Requires-Dist: shapely
Requires-Dist: scipy
Requires-Dist: netCDF4
Requires-Dist: pyyaml
Requires-Dist: appdirs
Requires-Dist: aiohttp
Requires-Dist: aiofiles
Requires-Dist: pytest
Requires-Dist: tqdm
Requires-Dist: requests
Dynamic: license-file
